<?xml version="1.0" encoding="utf-8"?>
<PASS_HEAD>
  <GATEPASS_NO>
  </GATEPASS_NO>
  <CORP_NO>AI161201658</CORP_NO>
  <GOODS_NATURE_ID>3</GOODS_NATURE_ID>
  <PROVIDER_NAME>电子零件</PROVIDER_NAME>
  <D_DATE>2016-12-07</D_DATE>
  <I_E_FALG_TYPE>I</I_E_FALG_TYPE>
  <TRANSPORT_CODE>3223980002</TRANSPORT_CODE>
  <TRANSPORT_NAME>江苏飞力达国际物流股份有限公司</TRANSPORT_NAME>
  <APPCOMPANY>3223980002</APPCOMPANY>
  <APPCOMPANY_NAME>江苏飞力达国际物流股份有限公司</APPCOMPANY_NAME>
  <APPCIQID>236920161696458359</APPCIQID>
  <BIZ_TYPE_ID>R</BIZ_TYPE_ID>
  <BIZ_TYPE_NAME>
  </BIZ_TYPE_NAME>
  <TRADE_CODE>3223640105</TRADE_CODE>
  <TRADE_NAME>启新通讯(昆山)有限公司</TRADE_NAME>
  <CONSIGNEE_CODE>3223640105</CONSIGNEE_CODE>
  <CONSIGNEE_NAME>启新通讯(昆山)有限公司</CONSIGNEE_NAME>
  <TRADE_CODE_IN>3223640105</TRADE_CODE_IN>
  <TRADE_NAME_IN>启新通讯(昆山)有限公司</TRADE_NAME_IN>
  <PACK_NO>1</PACK_NO>
  <GROSS_WT>11.05</GROSS_WT>
  <NET_WT>11.05</NET_WT>
  <TRAFFICTYPE>5</TRAFFICTYPE>
  <BILL_TYPE>1</BILL_TYPE>
  <ENTRY_ID_OUT>
  </ENTRY_ID_OUT>
  <APPCIQTYPE>0</APPCIQTYPE>
  <WRAP_TYPE_ID>2</WRAP_TYPE_ID>
  <MAINCODE>11217481181</MAINCODE>
  <SUBCODE>3219606460</SUBCODE>
  <MANUAL_NO>
  </MANUAL_NO>
  <OUT_CODE>
  </OUT_CODE>
  <TRANSFER_NO>
  </TRANSFER_NO>
  <GOODS_TYPE_LY>22</GOODS_TYPE_LY>
  <ISHDZ>
  </ISHDZ>
  <TRADETYPE>
  </TRADETYPE>
  <OUT_GOODS_TYPE_LY>
  </OUT_GOODS_TYPE_LY>
  <LY_BIZ_TYPE_ID>03</LY_BIZ_TYPE_ID>
  <GOODS_TYPE_ID>01</GOODS_TYPE_ID>
  <LYTYPE_ID>1</LYTYPE_ID>
  <AREA_CODE>
  </AREA_CODE>
  <MEANSOFTRANSPORTNAME>
  </MEANSOFTRANSPORTNAME>
  <MEANSOFTRANSPORTID>
  </MEANSOFTRANSPORTID>
  <REMARK>
  </REMARK>
  <FULL_NO_ZD>
  </FULL_NO_ZD>
  <OUT_TRAF_MODE>
  </OUT_TRAF_MODE>
  <IS_BLR>
  </IS_BLR>
  <SEND_USER>
  </SEND_USER>
  <SEND_TIME>
  </SEND_TIME>
</PASS_HEAD>